astars/__init__.py
astars-0.0.1.dist-info/METADATA
astars-0.0.1.dist-info/WHEEL
astars-0.0.1.dist-info/top_level.txt
astars-0.0.1.dist-info/RECORD
